{
  "fetched_at": "2026-06-29T01:35:40.109Z",
  "source": "CoinGecko (free)",
  "derivatives": [
    {
      "name": "Binance (Futures)",
      "oi_btc": 366560.96,
      "vol24h_btc": "465111.77",
      "perps": 593
    },
    {
      "name": "Bybit (Futures)",
      "oi_btc": 152194.77,
      "vol24h_btc": "128066.04",
      "perps": 701
    },
    {
      "name": "Hyperliquid (Futures)",
      "oi_btc": 151582.1,
      "vol24h_btc": "59703.62",
      "perps": 365
    },
    {
      "name": "MEXC (Futures)",
      "oi_btc": 148455.7,
      "vol24h_btc": "138366.06",
      "perps": 981
    },
    {
      "name": "CoinW (Futures)",
      "oi_btc": 146127.21,
      "vol24h_btc": "269418.74",
      "perps": 275
    },
    {
      "name": "Gate (Futures)",
      "oi_btc": 127777.25,
      "vol24h_btc": "125773.88",
      "perps": 828
    },
    {
      "name": "WEEX (Futures)",
      "oi_btc": 109026.47,
      "vol24h_btc": "168582.32",
      "perps": 833
    },
    {
      "name": "Bitmart Futures",
      "oi_btc": 108431.47,
      "vol24h_btc": "76509.67",
      "perps": 891
    },
    {
      "name": "XT.COM (Derivatives)",
      "oi_btc": 105571.49,
      "vol24h_btc": "68278.17",
      "perps": 686
    },
    {
      "name": "Bitget Futures",
      "oi_btc": 102910.26,
      "vol24h_btc": "79571.23",
      "perps": 743
    },
    {
      "name": "Deribit",
      "oi_btc": 101837.02,
      "vol24h_btc": "3673.5",
      "perps": 21
    },
    {
      "name": "OKX (Futures)",
      "oi_btc": 101531.9,
      "vol24h_btc": "225867.71",
      "perps": 404
    },
    {
      "name": "BYDFi (Futures)",
      "oi_btc": 94838.72,
      "vol24h_btc": "3291.03",
      "perps": 535
    },
    {
      "name": "KuCoin Futures",
      "oi_btc": 90273.01,
      "vol24h_btc": "21154.73",
      "perps": 661
    },
    {
      "name": "Toobit Futures",
      "oi_btc": 73147.42,
      "vol24h_btc": "204012.49",
      "perps": 685
    },
    {
      "name": "WhiteBIT Futures",
      "oi_btc": 64749.16,
      "vol24h_btc": "109287.88",
      "perps": 375
    },
    {
      "name": "HTX Futures",
      "oi_btc": 56557.16,
      "vol24h_btc": "18604.2",
      "perps": 305
    },
    {
      "name": "CoinUp.io (Futures)",
      "oi_btc": 47358.84,
      "vol24h_btc": "148524.48",
      "perps": 108
    },
    {
      "name": "BingX (Futures)",
      "oi_btc": 45970.27,
      "vol24h_btc": "81161.39",
      "perps": 823
    },
    {
      "name": "Phemex (Futures)",
      "oi_btc": 41005.93,
      "vol24h_btc": "24703.14",
      "perps": 589
    }
  ],
  "prices": {
    "bitcoin": {
      "usd": 59203,
      "usd_market_cap": 1187450866511.256,
      "usd_24h_change": -1.5642658342428075
    },
    "ethereum": {
      "usd": 1561.69,
      "usd_market_cap": 188537587710.1809,
      "usd_24h_change": -0.7591589214850542
    },
    "hyperliquid": {
      "usd": 61.29,
      "usd_market_cap": 13636558720.57565,
      "usd_24h_change": -0.6831955760691957
    },
    "solana": {
      "usd": 71.04,
      "usd_market_cap": 41264540273.680275,
      "usd_24h_change": 0.5082276114284484
    }
  },
  "global": {
    "total_mcap_usd": 2135430945612.7656,
    "mcap_change_24h_pct": -1.1068289088816012,
    "btc_dominance_pct": 55.64270947009656
  }
}